lockdoor-2.3.1.data/scripts/lockdoor
lockdoors/__init__.py
lockdoors/about.py
lockdoors/encdyc.py
lockdoors/exploitation.py
lockdoors/infogathering.py
lockdoors/main.py
lockdoors/passattack.py
lockdoors/privesc.py
lockdoors/psafrt.py
lockdoors/reverse.py
lockdoors/sanitize.py
lockdoors/shells.py
lockdoors/shrts.py
lockdoors/soceng.py
lockdoors/update.py
lockdoors/webhack.py
lockdoors/wtpp.py
lockdoor-2.3.1.dist-info/LICENSE
lockdoor-2.3.1.dist-info/METADATA
lockdoor-2.3.1.dist-info/WHEEL
lockdoor-2.3.1.dist-info/top_level.txt
lockdoor-2.3.1.dist-info/RECORD
