Metadata-Version: 2.1
Name: lockdoor
Version: 2.3.1
Summary: Lockdoor Framework : A Penetration Testing framework
Home-page: https://github.com/SofianeHamlaoui/Lockdoor-Framework
Author: Sofiane Hamlaoui
Author-email: s0fianehaml40u1@gmail.com
License: GPL-3.0
Platform: UNKNOWN
Classifier: Programming Language :: Python :: 3
Classifier: License :: OSI Approved :: GNU General Public License v3 (GPLv3)
Classifier: Operating System :: OS Independent
License-File: LICENSE
Requires-Dist: requests
